contrib/__init__.py
contrib/config.py
contrib/main.py
contrib-0.3.0.data/scripts/contrib
contrib-0.3.0.dist-info/LICENSE-APACHE
contrib-0.3.0.dist-info/LICENSE-MIT
contrib-0.3.0.dist-info/METADATA
contrib-0.3.0.dist-info/NOTICE
contrib-0.3.0.dist-info/WHEEL
contrib-0.3.0.dist-info/top_level.txt
contrib-0.3.0.dist-info/RECORD
