Metadata-Version: 2.1
Name: contrib
Version: 0.3.0
Summary: A python package for making stacked area plots of contributions over time.
Home-page: https://github.com/spack/contrib
Author: Todd Gamblin
Author-email: tgamblin@llnl.gov
License: Apache-2.0 OR MIT
Platform: UNKNOWN
Classifier: Development Status :: 3 - Alpha
Requires-Python: >=3.6
